elegoo_robot_car4/__init__.py
elegoo_robot_car4/car.py
elegoo_robot_car4/elegoo_smartcar_control.py
elegoo_robot_car4-0.3.0.dist-info/licenses/LICENSE
elegoo_robot_car4-0.3.0.dist-info/WHEEL
elegoo_robot_car4-0.3.0.dist-info/entry_points.txt
elegoo_robot_car4-0.3.0.dist-info/METADATA
elegoo_robot_car4-0.3.0.dist-info/RECORD
