Metadata-Version: 2.4
Name: elegoo-robot-car4
Version: 0.3.0
Summary: Python software for controlling the Elegoo Smart Robot Car V4.0
Author: Michele De Stefano
License-Expression: MIT
License-File: LICENSE
Classifier: Development Status :: 4 - Beta
Classifier: Intended Audience :: Developers
Classifier: Intended Audience :: Science/Research
Classifier: Intended Audience :: Education
Classifier: Programming Language :: Python :: 3
Classifier: Operating System :: OS Independent
Classifier: Topic :: Scientific/Engineering
Requires-Dist: lap>=0.5.12
Requires-Dist: opencv-python>=4.13.0.90
Requires-Dist: pygame-ce>=2.5.6
Requires-Dist: requests>=2.32.5
Requires-Dist: scipy>=1.17.0
Requires-Dist: torch>=2.10.0
Requires-Dist: torchvision>=0.25.0
Requires-Dist: ultralytics>=8.4.8
Requires-Python: >=3.12
Project-URL: Homepage, https://github.com/micdestefano/elegoo-robot-car4
Project-URL: Documentation, https://github.com/micdestefano/elegoo-robot-car4/blob/main/README.md
Project-URL: Download, https://pypi.org/project/elegoo-robot-car4/#files
Project-URL: Source, https://github.com/micdestefano/elegoo-robot-car4
Project-URL: Issues, https://github.com/micdestefano/elegoo-robot-car4/issues
